pyqie-0.0.4.dist-info/METADATA
pyqie-0.0.4.dist-info/WHEEL
pyqie-0.0.4.dist-info/entry_points.txt
pyqie-0.0.4.dist-info/license_files/LICENSE
pyqie/cli.py
pyqie/esper.py
pyqie/examples/01_hello_pyqie.py
pyqie/examples/02_hello_esper.py
pyqie/hello.py
pyqie/hello.pyi
pyqie/hello_test.py
pyqie/py.typed
pyqie/utils.py
pyqie/__init__.py
pyqie/__init__.pyi
pyqie/__main__.py
pyqie/pyqie_wrapper.pyd
pyqie-0.0.4.dist-info/RECORD
