Metadata-Version: 2.3
Name: pyqie
Version: 0.0.4
Classifier: Development Status :: 5 - Production/Stable
Classifier: License :: OSI Approved :: MIT License
Classifier: Operating System :: MacOS
Classifier: Operating System :: Microsoft :: Windows
Classifier: Operating System :: POSIX :: Linux
Classifier: Programming Language :: Python
Classifier: Programming Language :: Rust
License-File: LICENSE
Summary: A retro game engine for Python
Keywords: quantdev,python
Author: Takashi Kitao <takashi.xiatian0716@gmail.com>
Author-email: xiatian0716 <takashi.xiatian0716@gmail.com>
License: MIT
Requires-Python: >=3.7
Project-URL: homepage, https://github.com/xiatian0716/pyqie
